micromodel/__init__.py
micromodel/micromodel.py
micromodel-0.0.0.dist-info/LICENSE
micromodel-0.0.0.dist-info/METADATA
micromodel-0.0.0.dist-info/WHEEL
micromodel-0.0.0.dist-info/top_level.txt
micromodel-0.0.0.dist-info/RECORD
