Metadata-Version: 2.1
Name: micromodel
Version: 0.0.0
Summary: todo
Author-email: João Gabriel Santos <joaosan177@gmail.com>
Project-URL: Homepage, https://github.com/capsulbrasil/micromodel
Classifier: Programming Language :: Python :: 3
Classifier: License :: OSI Approved :: MIT License
Classifier: Operating System :: OS Independent
Requires-Python: >=3.11
License-File: LICENSE
